pybrainlife/__init__.py
pybrainlife/data/collect.py
pybrainlife/data/manipulate.py
pybrainlife/vis/plots.py
pybrainlife-1.1.41.dist-info/METADATA
pybrainlife-1.1.41.dist-info/WHEEL
pybrainlife-1.1.41.dist-info/RECORD
