Metadata-Version: 2.1
Name: pybrainlife
Version: 1.1.41
Summary: This project is a collection of functions that are useful for analyzing MRI data derivatives generated on brainlife.io
Home-page: https://github.com/brainlife/pybrainlife
Keywords: brainlife
Author: Brad Caron
Author-email: bacaron245@gmail.com
Requires-Python: >=3.8,<4.0
Classifier: Programming Language :: Python :: 3
Classifier: Programming Language :: Python :: 3.8
Classifier: Programming Language :: Python :: 3.9
Classifier: Programming Language :: Python :: 3.10
Classifier: Programming Language :: Python :: 3.11
Requires-Dist: bctpy (>=0.6.0,<0.7.0)
Requires-Dist: jgf (>=0.2.2,<0.3.0)
Requires-Dist: matplotlib (>=3.5.3,<4.0.0)
Requires-Dist: numpy (>=1.9.3,<2.0.0)
Requires-Dist: pandas (>=1.4.3,<2.0.0)
Requires-Dist: requests (>=2.28.1,<3.0.0)
Requires-Dist: scikit-learn (>=1.0.2,<2.0.0)
Requires-Dist: scipy (>=1.8.0,<2.0.0)
Requires-Dist: seaborn (>=0.12.2,<0.13.0)
Project-URL: Repository, https://github.com/brainlife/pybrainlife
